Group05_Lab5_part4/part4/group05_lab5_part1.v


module ALU(DATA1,DATA2,RESULT,SELECT,ZERO);

input wire[7:0] DATA1,DATA2; // Declaring an input wire-buses DATA1 and DATA2
input wire[2:0] SELECT; // Declaring an input wire-buse SELECT
output reg[7:0] RESULT; // Declaring an output RESULT as a reg
wire [7:0] FORWARD_wire,ADD_wire,AND_wire,OR_wire; // Declaring wires which connects the multiplexer and Circuits which implement FORWARD,AND,ADD,OR operations
output reg ZERO ;

forward f1(DATA2,FORWARD_wire); //Creating an instance of forward module
adder f2(DATA1,DATA2,ADD_wire); //Creating an instance of adder module
AND f3(DATA1,DATA2,AND_wire); //Creating an instance of AND module
OR f4(DATA1,DATA2,OR_wire); //Creating an instance of OR module

//Implementing a multiplexer to select the algrebric operation we need according to SELECT signal
always @(DATA1 or DATA2 or SELECT) begin
    
     case (SELECT)
         3'b000: assign RESULT = FORWARD_wire;
         3'b001: assign RESULT = ADD_wire;
         3'b010: assign RESULT = AND_wire;
         3'b011: assign RESULT = OR_wire;
         default: assign RESULT = 8'bxxxxxxxx; //If SELECT is neither 000,001,010,011, operations to other codes are not assigned yet. Hence Unknown result is generated.
     endcase

end

always @(RESULT) begin
    if (RESULT == 8'b00000000) begin
        ZERO  = 1'b1 ;
     end else begin
        ZERO = 1'b0 ;
     end    
end

endmodule

//Module which implemented ADD operation
module adder(DATA1,DATA2,RESULT);
    input wire[7:0] DATA1,DATA2;
    output wire[7:0] RESULT;

    assign #2 RESULT = DATA1+DATA2; //Adding DATA1 and DATA2 inputs with a delay
endmodule

//Module which implemented FORWARD operation
module forward(DATA2,RESULT);
    input wire[7:0] DATA2;
    output wire[7:0] RESULT;

    assign #1 RESULT = DATA2; //Assigning DATA2 to RESULT
endmodule

//Module which implemented AND operation
module AND (DATA1,DATA2,RESULT);
    input wire[7:0] DATA1,DATA2;
    output wire[7:0] RESULT;
    
    assign #1 RESULT = DATA1 & DATA2; //AND DATA1 and DATA2 inputs with a delay
endmodule

//Module which implemented OR operation
module OR (DATA1,DATA2,RESULT);
    input wire[7:0] DATA1,DATA2;
    output wire[7:0] RESULT;
    
    assign #1 RESULT = DATA1 | DATA2; //OR DATA1 and DATA2 inputs with a delay
endmodule

group05_lab06_part02/group05_lab06_part02/group05_lab5_part2.v
`timescale 1ns/100ps

module reg_file(IN, OUT1, OUT2, INADDRESS, OUT1ADDRESS, OUT2ADDRESS, WRITE, CLK, RESET);
    input[7:0] IN; // Declaring an input wire-bus to take WRITEDATA signals
    input[2:0] OUT1ADDRESS,OUT2ADDRESS,INADDRESS; // Declaring an input wire-bus to take WRITEDATA signals
    input CLK,WRITE,RESET; // Declaring clock pulse wire, WRITE_ENABLE wire and RESET wire as input 
    output reg [7:0] OUT1,OUT2;  // Declaring REGOUT1 and REGOUT2 signals as register outputs
    reg[7:0] register[0:7]; // Declaring register0-register7 as an array of words 

    //For rising edges of clock pulse
    always @(posedge CLK) begin
        if(RESET==1)begin //When RESET = 1 clearing registers with a delay

            #1
             register[0]<=0;
             register[1]<=0;
             register[2]<=0;
             register[3]<=0;
             register[4]<=0;
             register[5]<=0;
             register[6]<=0;
             register[7]<=0;
        end
        else if(WRITE==1)begin // When WRITE_ENABLE = 1 writing to a specific register
            
            case(INADDRESS) //Choosing the register to be written by considering the INADDRESS signal
                3'b000:#1 register[0] <= IN;
                3'b001:#1 register[1] <= IN;
                3'b010:#1 register[2] <= IN;
                3'b011:#1 register[3] <= IN;
                3'b100:#1 register[4] <= IN;
                3'b101:#1 register[5] <= IN;
                3'b110:#1 register[6] <= IN;
                3'b111:#1 register[7] <= IN;
                default:;
            endcase
        end
        
    end

    //When changes occur in registers register0-register7 or OUT1ADDRESS, asynchrous reading operating takes place.
    always @(OUT2ADDRESS,OUT1ADDRESS,register[0],register[1],register[2],register[3],register[4],register[5],register[6],register[7]) begin
        case (OUT1ADDRESS) //Choosing the register to be read by considering the OUT1ADDRESS signal
            3'b000:#2 OUT1 = register[0];
            3'b001:#2 OUT1 = register[1];
            3'b010:#2 OUT1 = register[2];
            3'b011:#2 OUT1 = register[3];
            3'b100:#2 OUT1 = register[4];
            3'b101:#2 OUT1 = register[5];
            3'b110:#2 OUT1 = register[6];
            3'b111:#2 OUT1 = register[7]; 
            default:; 
        endcase
    end

    //When changes occur in registers register0-register7 or OUT2ADDRESS, asynchrous reading operating takes place.
    always @(OUT1ADDRESS,OUT2ADDRESS,register[0],register[1],register[2],register[3],register[4],register[5],register[6],register[7]) begin
        case (OUT2ADDRESS) //Choosing the register to be read by considering the OUT2ADDRESS signal
            3'b000:#2 OUT2 = register[0];
            3'b001:#2 OUT2 = register[1];
            3'b010:#2 OUT2 = register[2];
            3'b011:#2 OUT2 = register[3];
            3'b100:#2 OUT2 = register[4];
            3'b101:#2 OUT2 = register[5];
            3'b110:#2 OUT2 = register[6];
            3'b111:#2 OUT2 = register[7]; 
            default:; 
        endcase      
    end

endmodule

Group05_Lab5_part4/part4/group05_lab5_part3.v
//module for the cpu
module cpu(PC , INSTRUCTION , CLK ,RESET) ;
    //declare inputs and outputs 
    input CLK, RESET;
    output [31:0] PC;
    input wire [31:0] INSTRUCTION;

    //declare respective wires

    wire [2:0] READREG1 , READREG2 , WRITEREG ;
    wire [7:0] OPCODE , IMMEDIATE , offset;
    
    wire [2:0] ALUOP , PC_select;
    wire MUX1_select , MUX2_select , WRITEENABLE ,ZERO  ;

    wire [7:0] ALURESULT , REGOUT1 , REGOUT2 ;
    
    wire [7:0] REGOUT2_2scomp ;

    wire [7:0] mux1_OUTPUT ;

    wire [7:0] mux2_OUTPUT ;

    wire [31:0] PC_val , PC_target , PC_next;

    //break the instruction to resoective parts and assign for the wires 
    assign READREG2[2:0] = INSTRUCTION[2:0] ;
    assign READREG1[2:0] = INSTRUCTION[10:8] ;
    assign WRITEREG[2:0] = INSTRUCTION[18:16] ;
    assign OPCODE[7:0] = INSTRUCTION[31:24] ;
    assign IMMEDIATE[7:0] = INSTRUCTION[7:0] ;
    assign offset[7:0] = INSTRUCTION[23:16] ;


    //call the respective modules and instantiate respective modules
    pc myPC(CLK , RESET , PC , PC_next);
    Control_Unit my_Control_Unit(OPCODE , WRITEENABLE , ALUOP , MUX1_select , MUX2_select ,PC_select);
    reg_file my_reg(ALURESULT, REGOUT1, REGOUT2, WRITEREG, READREG1, READREG2, WRITEENABLE, CLK, RESET);
    TWOS_Comp my_TWOS_Comp(REGOUT2 , REGOUT2_2scomp);
    MUX_7x2x1 my_mux1(REGOUT2 , REGOUT2_2scomp , mux1_OUTPUT , MUX1_select);
    MUX_7x2x1 my_mux2(IMMEDIATE , mux1_OUTPUT , mux2_OUTPUT , MUX2_select);
    ALU my_ALU(REGOUT1,mux2_OUTPUT,ALURESULT,ALUOP,ZERO);
    PC_getTarget my_PC_getTarget(PC ,PC_val , offset ,PC_target ) ;
    PC_next_select my_PC_next_select(PC_select , ZERO , PC_next , PC_val , PC_target);

endmodule

//module for the program counter
module pc (CLK , RESET , PC  ,PC_next);
    input CLK ,RESET;
    output reg[31:0] PC ;
    input [31: 0] PC_next ; // gives the next PC value


    always @(posedge CLK) begin
        if ( RESET == 1'b1 ) begin
            #1 PC = 32'b00000000000000000000000000000000;
        end else  begin
            #1 PC = PC_next ;
        end  
        
    end

    
endmodule


//module for the control unit
module Control_Unit (OPCODE , WRITEENABLE , ALUOP , MUX1_select , MUX2_select ,PC_select );
    input [7:0]OPCODE ;
    output reg [2:0] ALUOP , PC_select ;
    output reg MUX1_select , MUX2_select , WRITEENABLE  ;


    always @(OPCODE) begin //selecting respective selecting signals

        case(OPCODE) 
                8'b00000000: begin //loadi
                    #1 
                    WRITEENABLE <= 1'b1; 
                    ALUOP <= 3'b000 ; 
                    //MUX1_select <= 1'b1 ; 
                    MUX2_select <= 1'b1 ; 
                    PC_select <= 3'b000 ;
                
                    end

                8'b00000001: begin //mov
                    #1 
                    WRITEENABLE <= 1'b1; 
                    ALUOP <= 3'b000 ; 
                    MUX1_select <= 1'b1 ; 
                    MUX2_select <= 1'b0 ; 
                    PC_select <= 3'b000 ;
                   
                    end

                8'b00000010: begin //add
                    #1 
                    WRITEENABLE <= 1'b1; 
                    ALUOP <= 3'b001 ; 
                    MUX1_select <= 1'b1 ; 
                    MUX2_select <= 1'b0 ;
                    PC_select <= 3'b000 ; 
                  
                    end

                8'b00000011: begin //sub
                    #1 
                    WRITEENABLE <= 1'b1; 
                    ALUOP <= 3'b001 ; 
                    MUX1_select <= 1'b0 ; 
                    MUX2_select <= 1'b0 ;
                    PC_select <= 3'b000 ; 
                    
                    end

                8'b00000100: begin //and
                    #1 
                    WRITEENABLE <= 1'b1; 
                    ALUOP <= 3'b010 ; 
                    MUX1_select <= 1'b1 ; 
                    MUX2_select <= 1'b0 ;
                    PC_select <= 3'b000 ; 
                  
                    end

                8'b00000101: begin //or
                    #1 
                    WRITEENABLE <= 1'b1; 
                    ALUOP <= 3'b011 ; 
                    MUX1_select <= 1'b1 ; 
                    MUX2_select <= 1'b0 ;
                    PC_select <= 3'b000 ; 
                    
                    end

                8'b00000110: begin // j
                    #1 
                    WRITEENABLE <= 1'b0; 
                    PC_select <= 3'b001 ; 
                  
                    end

                8'b00000111: begin // beq
                    #1 
                    WRITEENABLE <= 1'b0; 
                    PC_select <= 3'b010 ; 
                    ALUOP <= 3'b001 ; 
                    MUX1_select <= 1'b0 ; 
                    MUX2_select <= 1'b0 ;
                   

                    end

                default: begin
                    #1 
                    WRITEENABLE <= 1'b0; 
                    PC_select <= 3'b000 ; 
                    
                end
                
        endcase
    end

endmodule

//module for the 2s complement
module TWOS_Comp (REGOUT2 , REGOUT2_2scomp);
    input [7:0] REGOUT2 ;
    output [7:0] REGOUT2_2scomp ;

    assign #1  REGOUT2_2scomp = ~REGOUT2 + 8'b00000001  ;

endmodule



//module for the mux
module MUX_7x2x1 (INPUT1 , INPUT2 , OUTPUT , SELECT);
    input [7:0] INPUT1 , INPUT2 ;
    input SELECT ;
    output reg [7:0] OUTPUT ;

    always @(INPUT1 , INPUT2,SELECT) begin
        if(SELECT==1'b1)begin
            assign OUTPUT = INPUT1;
        end else if (SELECT==1'b0) begin
            assign OUTPUT = INPUT2;
        end
    end

endmodule


//module for next PC value
module PC_next_select(PC_select , ZERO , PC_next , PC_val , PC_target);
    input [31:0] PC_val , PC_target ;
    input [2:0] PC_select ;
    input ZERO ;
    output reg [31:0] PC_next ;

    always @(PC_select , ZERO , PC_val , PC_target) begin
        if(PC_select==3'b001)begin
            PC_next = PC_target ;
        end else if (PC_select==3'b010 && ZERO==1'b1) begin
            PC_next = PC_target;
        end else begin
            PC_next = PC_val;
        end
    end

endmodule

// module for the branch and the jump
module PC_getTarget(PC ,PC_val , offset ,PC_target ) ; //offset is from instruction
    output reg [31:0] PC_val ;
    input [7:0] offset ;
    input [31:0] PC ;
    output reg [31:0] PC_target ;
    reg [31:0] temp;
    
    always @(offset , PC_val) begin
        if(offset[7] == 1'b0) begin
            temp[31:10] <= 22'b0000000000000000000000 ;
            temp[9:2] <= offset[7:0] ;
            temp[1:0] <= 2'b00 ;
        end else if (offset[7] == 1'b1) begin
            temp[31:10] <= 22'b1111111111111111111111 ;
            temp[9:2] <= offset[7:0] ;
            temp[1:0] <= 2'b00 ;
        end
    end 

    always @(temp) begin
        #2 PC_target = PC_val + temp ;
    end

    always @(PC) begin
        #1 PC_val = PC + 32'd4 ;
    end

endmodule 




// Computer Architecture (CO224) - Lab 05
// Design: Testbench of Integrated CPU of Simple Processor
// Author: Isuru Nawinne


module cpu_tb;

    reg CLK, RESET;
    wire [31:0] PC;
    reg [31:0] INSTRUCTION;
    reg [7:0] instr_mem [1024:0] ;
    
    /* 
    ------------------------
     SIMPLE INSTRUCTION MEM
    ------------------------
    */
    
    // TODO: Initialize an array of registers (8x1024) named 'instr_mem' to be used as instruction memory
    
    // TODO: Create combinational logic to support CPU instruction fetching, given the Program Counter(PC) value 
    //       (make sure you include the delay for instruction fetching here)
    
    always @(PC) begin
        #2
        INSTRUCTION[7:0]<=instr_mem[PC] ;
        INSTRUCTION[15:8]<=instr_mem[PC+31'd1] ;
        INSTRUCTION[23:16]<=instr_mem[PC+31'd2] ;
        INSTRUCTION[31:24]<=instr_mem[PC+31'd3] ;
    end

    initial
    begin
        // Initialize instruction memory with the set of instructions you need execute on CPU
        
        // METHOD 1: manually loading instructions to instr_mem
        //{instr_mem[10'd3], instr_mem[10'd2], instr_mem[10'd1], instr_mem[10'd0]} = 32'b00000000000001000000000000000101;
        //{instr_mem[10'd7], instr_mem[10'd6], instr_mem[10'd5], instr_mem[10'd4]} = 32'b00000000000000100000000000001001;
        //{instr_mem[10'd11], instr_mem[10'd10], instr_mem[10'd9], instr_mem[10'd8]} = 32'b00000010000001100000010000000010;
        
        // METHOD 2: loading instr_mem content from instr_mem.mem file
        $readmemb("instr_mem.mem", instr_mem,0,256);
    end
    
    /* 
    -----
     CPU
    -----
    */
    cpu mycpu(PC, INSTRUCTION, CLK, RESET);
    

    initial
    begin
    
        // generate files needed to plot the waveform using GTKWave
        $dumpfile("cpu_wavedata.vcd");
		$dumpvars(0, cpu_tb);
        
        CLK = 1'b0;
        //RESET = 1'b0;

        RESET = 1'b1;
        #10 RESET = 1'b0;
        
        // TODO: Reset the CPU (by giving a pulse to RESET signal) to start the program execution
        
        // finish simulation after some time
        #500
        $finish;
        
    end
    
    // clock signal generation
    always
        #4 CLK = ~CLK;
        

endmodule

Group05_Lab5_part4/part4/cpu_wavedata.vcd
$date
	Wed Feb 02 00:42:22 2022
$end
$version
	Icarus Verilog
$end
$timescale
	1s
$end
$scope module cpu_tb $end
$var wire 32 ! PC [31:0] $end
$var reg 1 " CLK $end
$var reg 32 # INSTRUCTION [31:0] $end
$var reg 1 $ RESET $end
$scope module mycpu $end
$var wire 1 " CLK $end
$var wire 32 % INSTRUCTION [31:0] $end
$var wire 1 $ RESET $end
$var wire 8 & offset [7:0] $end
$var wire 8 ' mux2_OUTPUT [7:0] $end
$var wire 8 ( mux1_OUTPUT [7:0] $end
$var wire 1 ) ZERO $end
$var wire 3 * WRITEREG [2:0] $end
$var wire 1 + WRITEENABLE $end
$var wire 8 , REGOUT2_2scomp [7:0] $end
$var wire 8 - REGOUT2 [7:0] $end
$var wire 8 . REGOUT1 [7:0] $end
$var wire 3 / READREG2 [2:0] $end
$var wire 3 0 READREG1 [2:0] $end
$var wire 32 1 PC_val [31:0] $end
$var wire 32 2 PC_target [31:0] $end
$var wire 3 3 PC_select [2:0] $end
$var wire 32 4 PC_next [31:0] $end
$var wire 32 5 PC [31:0] $end
$var wire 8 6 OPCODE [7:0] $end
$var wire 1 7 MUX2_select $end
$var wire 1 8 MUX1_select $end
$var wire 8 9 IMMEDIATE [7:0] $end
$var wire 8 : ALURESULT [7:0] $end
$var wire 3 ; ALUOP [2:0] $end
$scope module myPC $end
$var wire 1 " CLK $end
$var wire 1 $ RESET $end
$var wire 32 < PC_next [31:0] $end
$var reg 32 = PC [31:0] $end
$upscope $end
$scope module my_ALU $end
$var wire 3 > SELECT [2:0] $end
$var wire 8 ? OR_wire [7:0] $end
$var wire 8 @ FORWARD_wire [7:0] $end
$var wire 8 A DATA2 [7:0] $end
$var wire 8 B DATA1 [7:0] $end
$var wire 8 C AND_wire [7:0] $end
$var wire 8 D ADD_wire [7:0] $end
$var reg 8 E RESULT [7:0] $end
$var reg 1 ) ZERO $end
$scope module f1 $end
$var wire 8 F RESULT [7:0] $end
$var wire 8 G DATA2 [7:0] $end
$upscope $end
$scope module f2 $end
$var wire 8 H RESULT [7:0] $end
$var wire 8 I DATA2 [7:0] $end
$var wire 8 J DATA1 [7:0] $end
$upscope $end
$scope module f3 $end
$var wire 8 K RESULT [7:0] $end
$var wire 8 L DATA2 [7:0] $end
$var wire 8 M DATA1 [7:0] $end
$upscope $end
$scope module f4 $end
$var wire 8 N RESULT [7:0] $end
$var wire 8 O DATA2 [7:0] $end
$var wire 8 P DATA1 [7:0] $end
$upscope $end
$upscope $end
$scope module my_Control_Unit $end
$var wire 8 Q OPCODE [7:0] $end
$var reg 3 R ALUOP [2:0] $end
$var reg 1 8 MUX1_select $end
$var reg 1 7 MUX2_select $end
$var reg 3 S PC_select [2:0] $end
$var reg 1 + WRITEENABLE $end
$upscope $end
$scope module my_PC_getTarget $end
$var wire 32 T PC [31:0] $end
$var wire 8 U offset [7:0] $end
$var reg 32 V PC_target [31:0] $end
$var reg 32 W PC_val [31:0] $end
$var reg 32 X temp [31:0] $end
$upscope $end
$scope module my_PC_next_select $end
$var wire 3 Y PC_select [2:0] $end
$var wire 32 Z PC_target [31:0] $end
$var wire 32 [ PC_val [31:0] $end
$var wire 1 ) ZERO $end
$var reg 32 \ PC_next [31:0] $end
$upscope $end
$scope module my_TWOS_Comp $end
$var wire 8 ] REGOUT2_2scomp [7:0] $end
$var wire 8 ^ REGOUT2 [7:0] $end
$upscope $end
$scope module my_mux1 $end
$var wire 8 _ INPUT2 [7:0] $end
$var wire 1 8 SELECT $end
$var wire 8 ` INPUT1 [7:0] $end
$var reg 8 a OUTPUT [7:0] $end
$upscope $end
$scope module my_mux2 $end
$var wire 8 b INPUT1 [7:0] $end
$var wire 8 c INPUT2 [7:0] $end
$var wire 1 7 SELECT $end
$var reg 8 d OUTPUT [7:0] $end
$upscope $end
$scope module my_reg $end
$var wire 1 " CLK $end
$var wire 8 e IN [7:0] $end
$var wire 3 f INADDRESS [2:0] $end
$var wire 3 g OUT1ADDRESS [2:0] $end
$var wire 3 h OUT2ADDRESS [2:0] $end
$var wire 1 $ RESET $end
$var wire 1 + WRITE $end
$var reg 8 i OUT1 [7:0] $end
$var reg 8 j OUT2 [7:0] $end
$upscope $end
$upscope $end
$upscope $end
$enddefinitions $end
#0
$dumpvars
bx j
bx i
bx h
bx g
bx f
bx e
bx d
bx c
bx b
bx a
bx `
bx _
bx ^
bx ]
bx \
bx [
bx Z
bx Y
bx X
bx W
bx V
bx U
bx T
bx S
bx R
bx Q
bx P
bx O
bx N
bx M
bx L
bx K
bx J
bx I
bx H
bx G
bx F
bx E
bx D
bx C
bx B
bx A
bx @
bx ?
bx >
bx =
bx <
bx ;
bx :
bx 9
x8
x7
bx 6
bx 5
bx 4
bx 3
bx 2
bx 1
bx 0
bx /
bx .
bx -
bx ,
x+
bx *
x)
bx (
bx '
bx &
bx %
1$
bx #
0"
bx !
$end
#4
1"
#5
b0 !
b0 5
b0 =
b0 T
#6
b100 4
b100 <
b100 \
b100 1
b100 W
b100 [
#7
b0 X
b0 6
b0 Q
b0 *
b0 f
b0 &
b0 U
b0 0
b0 g
b101 /
b101 h
b101 9
b101 b
b101 #
b101 %
#8
b101 '
b101 A
b101 G
b101 I
b101 L
b101 O
b101 d
b0 3
b0 S
b0 Y
17
b0 ;
b0 >
b0 R
1+
0"
#9
0)
bx1x1 ?
bx1x1 N
b0x0x C
b0x0x K
b101 :
b101 E
b101 e
b101 @
b101 F
b100 2
b100 V
b100 Z
b0 .
b0 B
b0 J
b0 M
b0 P
b0 i
b0 -
b0 ^
b0 `
b0 j
#10
b101 ?
b101 N
b0 C
b0 K
b0 ,
b0 ]
b0 _
0$
#11
b101 D
b101 H
#12
1"
#13
b100 !
b100 5
b100 =
b100 T
#14
b1000 4
b1000 <
b1000 \
b1000 1
b1000 W
b1000 [
#15
b100 X
b1 6
b1 Q
b1 *
b1 f
b1 &
b1 U
b0 /
b0 h
b0 '
b0 A
b0 G
b0 I
b0 L
b0 O
b0 d
b0 9
b0 b
b1000000010000000000000000 #
b1000000010000000000000000 %
b101 .
b101 B
b101 J
b101 M
b101 P
b101 i
#16
b0 (
b0 a
b0 c
07
18
1)
b0 :
b0 E
b0 e
b0 @
b0 F
0"
#17
b1100 2
b1100 V
b1100 Z
b101 '
b101 A
b101 G
b101 I
b101 L
b101 O
b101 d
b101 (
b101 a
b101 c
b101 -
b101 ^
b101 `
b101 j
#18
0)
b11111011 ,
b11111011 ]
b11111011 _
b101 C
b101 K
b101 :
b101 E
b101 e
b101 @
b101 F
#19
b1010 D
b1010 H
#20
1"
#21
b1000 !
b1000 5
b1000 =
b1000 T
#22
b1100 4
b1100 <
b1100 \
b1100 1
b1100 W
b1100 [
#23
b1000 X
b0 6
b0 Q
b10 *
b10 f
b10 &
b10 U
b1 /
b1 h
b1001 9
b1001 b
b100000000000001001 #
b100000000000001001 %
#24
b1001 '
b1001 A
b1001 G
b1001 I
b1001 L
b1001 O
b1001 d
17
0"
#25
b1101 ?
b1101 N
b1 C
b1 K
b1001 :
b1001 E
b1001 e
b1001 @
b1001 F
b10100 2
b10100 V
b10100 Z
#26
b1110 D
b1110 H
#28
1"
#29
b1100 !
b1100 5
b1100 =
b1100 T
#30
b10000 4
b10000 <
b10000 \
b10000 1
b10000 W
b10000 [
#31
b1100 X
b10 6
b10 Q
b11 *
b11 f
b11 &
b11 U
b10 0
b10 g
b0 /
b0 h
b0 '
b0 A
b0 G
b0 I
b0 L
b0 O
b0 d
b0 9
b0 b
b10000000110000001000000000 #
b10000000110000001000000000 %
#32
b101 '
b101 A
b101 G
b101 I
b101 L
b101 O
b101 d
07
b1 ;
b1 >
b1 R
0)
b101 ?
b101 N
b0 C
b0 K
b1110 :
b1110 E
b1110 e
b0 @
b0 F
0"
#33
b101 C
b101 K
b101 @
b101 F
b11100 2
b11100 V
b11100 Z
b1001 .
b1001 B
b1001 J
b1001 M
b1001 P
b1001 i
#34
b1101 ?
b1101 N
b1 C
b1 K
#36
1"
#37
b10000 !
b10000 5
b10000 =
b10000 T
#38
b10100 4
b10100 <
b10100 \
b10100 1
b10100 W
b10100 [
#39
b10000 X
b11 6
b11 Q
b100 *
b100 f
b100 &
b100 U
b11 0
b11 g
b10 /
b10 h
b10 9
b10 b
b11000001000000001100000010 #
b11000001000000001100000010 %
#40
b11111011 '
b11111011 A
b11111011 G
b11111011 I
b11111011 L
b11111011 O
b11111011 d
b11111011 (
b11111011 a
b11111011 c
08
0"
#41
b11111011 ?
b11111011 N
b1001 C
b1001 K
b11111011 @
b11111011 F
b100100 2
b100100 V
b100100 Z
b1110 .
b1110 B
b1110 J
b1110 M
b1110 P
b1110 i
b1001 -
b1001 ^
b1001 `
b1001 j
#42
b11111111 ?
b11111111 N
b1010 C
b1010 K
b11110111 '
b11110111 A
b11110111 G
b11110111 I
b11110111 L
b11110111 O
b11110111 d
b11110111 (
b11110111 a
b11110111 c
b11110111 ,
b11110111 ]
b11110111 _
#43
b110 C
b110 K
b11110111 @
b11110111 F
#44
b101 :
b101 E
b101 e
b101 D
b101 H
1"
#45
b10100 !
b10100 5
b10100 =
b10100 T
#46
b11000 4
b11000 <
b11000 \
b11000 1
b11000 W
b11000 [
#47
b1000 X
b111 6
b111 Q
b10 *
b10 f
b10 &
b10 U
b0 0
b0 g
b1 /
b1 h
b1 9
b1 b
b111000000100000000000000001 #
b111000000100000000000000001 %
#48
b10 3
b10 S
b10 Y
0+
0"
#49
b100000 2
b100000 V
b100000 Z
b101 .
b101 B
b101 J
b101 M
b101 P
b101 i
b101 -
b101 ^
b101 `
b101 j
#50
b11110111 ?
b11110111 N
b101 C
b101 K
b11111011 '
b11111011 A
b11111011 G
b11111011 I
b11111011 L
b11111011 O
b11111011 d
b11111011 (
b11111011 a
b11111011 c
b11111011 ,
b11111011 ]
b11111011 _
#51
b11111111 ?
b11111111 N
b1 C
b1 K
b11111011 @
b11111011 F
#52
b100000 4
b100000 <
b100000 \
1)
b0 :
b0 E
b0 e
b0 D
b0 H
1"
#53
b100000 !
b100000 5
b100000 =
b100000 T
#54
b100100 1
b100100 W
b100100 [
#55
b100 X
b110 6
b110 Q
b1 *
b1 f
b1 &
b1 U
b0 /
b0 h
b0 9
b0 b
b110000000010000000000000000 #
b110000000010000000000000000 %
#56
b1 3
b1 S
b1 Y
0"
#57
b101000 4
b101000 <
b101000 \
b101000 2
b101000 V
b101000 Z
#60
1"
#61
b101000 !
b101000 5
b101000 =
b101000 T
#62
b101100 1
b101100 W
b101100 [
#63
b1 6
b1 Q
b1000000010000000000000000 #
b1000000010000000000000000 %
#64
0)
b101100 4
b101100 <
b101100 \
b101 '
b101 A
b101 G
b101 I
b101 L
b101 O
b101 d
b101 (
b101 a
b101 c
b11111011 :
b11111011 E
b11111011 e
b0 3
b0 S
b0 Y
18
b0 ;
b0 >
b0 R
1+
0"
#65
b101 ?
b101 N
b101 C
b101 K
b101 :
b101 E
b101 e
b101 @
b101 F
#66
b1010 D
b1010 H
#68
1"
#69
b101100 !
b101100 5
b101100 =
b101100 T
#70
b110000 4
b110000 <
b110000 \
b110000 1
b110000 W
b110000 [
#71
b1000 X
b0 6
b0 Q
b10 *
b10 f
b10 &
b10 U
b1 /
b1 h
b1001 9
b1001 b
b100000000000001001 #
b100000000000001001 %
#72
b1001 '
b1001 A
b1001 G
b1001 I
b1001 L
b1001 O
b1001 d
17
0"
#73
b1101 ?
b1101 N
b1 C
b1 K
b1001 :
b1001 E
b1001 e
b1001 @
b1001 F
b111000 2
b111000 V
b111000 Z
#74
b1110 D
b1110 H
#76
1"
#77
b110000 !
b110000 5
b110000 =
b110000 T
#78
b110100 4
b110100 <
b110100 \
b110100 1
b110100 W
b110100 [
#79
b1100 X
b10 6
b10 Q
b11 *
b11 f
b11 &
b11 U
b10 0
b10 g
b0 /
b0 h
b0 '
b0 A
b0 G
b0 I
b0 L
b0 O
b0 d
b0 9
b0 b
b10000000110000001000000000 #
b10000000110000001000000000 %
#80
b101 '
b101 A
b101 G
b101 I
b101 L
b101 O
b101 d
07
b1 ;
b1 >
b1 R
0)
b101 ?
b101 N
b0 C
b0 K
b1110 :
b1110 E
b1110 e
b0 @
b0 F
0"
#81
b101 C
b101 K
b101 @
b101 F
b1000000 2
b1000000 V
b1000000 Z
b1001 .
b1001 B
b1001 J
b1001 M
b1001 P
b1001 i
#82
b1101 ?
b1101 N
b1 C
b1 K
#84
1"
#85
b110100 !
b110100 5
b110100 =
b110100 T
#86
b111000 4
b111000 <
b111000 \
b111000 1
b111000 W
b111000 [
#87
bx 6
bx Q
bx *
bx f
bx &
bx U
bx 0
bx g
bx /
bx h
bx 9
bx b
bx #
bx %
#88
0+
0"
#92
1"
#93
b111000 !
b111000 5
b111000 =
b111000 T
#94
b111100 4
b111100 <
b111100 \
b111100 1
b111100 W
b111100 [
#96
0"
#100
1"
#101
b111100 !
b111100 5
b111100 =
b111100 T
#102
b1000000 4
b1000000 <
b1000000 \
b1000000 1
b1000000 W
b1000000 [
#104
0"
#108
1"
#109
b1000000 !
b1000000 5
b1000000 =
b1000000 T
#110
b1000100 4
b1000100 <
b1000100 \
b1000100 1
b1000100 W
b1000100 [
#112
0"
#116
1"
#117
b1000100 !
b1000100 5
b1000100 =
b1000100 T
#118
b1001000 4
b1001000 <
b1001000 \
b1001000 1
b1001000 W
b1001000 [
#120
0"
#124
1"
#125
b1001000 !
b1001000 5
b1001000 =
b1001000 T
#126
b1001100 4
b1001100 <
b1001100 \
b1001100 1
b1001100 W
b1001100 [
#128
0"
#132
1"
#133
b1001100 !
b1001100 5
b1001100 =
b1001100 T
#134
b1010000 4
b1010000 <
b1010000 \
b1010000 1
b1010000 W
b1010000 [
#136
0"
#140
1"
#141
b1010000 !
b1010000 5
b1010000 =
b1010000 T
#142
b1010100 4
b1010100 <
b1010100 \
b1010100 1
b1010100 W
b1010100 [
#144
0"
#148
1"
#149
b1010100 !
b1010100 5
b1010100 =
b1010100 T
#150
b1011000 4
b1011000 <
b1011000 \
b1011000 1
b1011000 W
b1011000 [
#152
0"
#156
1"
#157
b1011000 !
b1011000 5
b1011000 =
b1011000 T
#158
b1011100 4
b1011100 <
b1011100 \
b1011100 1
b1011100 W
b1011100 [
#160
0"
#164
1"
#165
b1011100 !
b1011100 5
b1011100 =
b1011100 T
#166
b1100000 4
b1100000 <
b1100000 \
b1100000 1
b1100000 W
b1100000 [
#168
0"
#172
1"
#173
b1100000 !
b1100000 5
b1100000 =
b1100000 T
#174
b1100100 4
b1100100 <
b1100100 \
b1100100 1
b1100100 W
b1100100 [
#176
0"
#180
1"
#181
b1100100 !
b1100100 5
b1100100 =
b1100100 T
#182
b1101000 4
b1101000 <
b1101000 \
b1101000 1
b1101000 W
b1101000 [
#184
0"
#188
1"
#189
b1101000 !
b1101000 5
b1101000 =
b1101000 T
#190
b1101100 4
b1101100 <
b1101100 \
b1101100 1
b1101100 W
b1101100 [
#192
0"
#196
1"
#197
b1101100 !
b1101100 5
b1101100 =
b1101100 T
#198
b1110000 4
b1110000 <
b1110000 \
b1110000 1
b1110000 W
b1110000 [
#200
0"
#204
1"
#205
b1110000 !
b1110000 5
b1110000 =
b1110000 T
#206
b1110100 4
b1110100 <
b1110100 \
b1110100 1
b1110100 W
b1110100 [
#208
0"
#212
1"
#213
b1110100 !
b1110100 5
b1110100 =
b1110100 T
#214
b1111000 4
b1111000 <
b1111000 \
b1111000 1
b1111000 W
b1111000 [
#216
0"
#220
1"
#221
b1111000 !
b1111000 5
b1111000 =
b1111000 T
#222
b1111100 4
b1111100 <
b1111100 \
b1111100 1
b1111100 W
b1111100 [
#224
0"
#228
1"
#229
b1111100 !
b1111100 5
b1111100 =
b1111100 T
#230
b10000000 4
b10000000 <
b10000000 \
b10000000 1
b10000000 W
b10000000 [
#232
0"
#236
1"
#237
b10000000 !
b10000000 5
b10000000 =
b10000000 T
#238
b10000100 4
b10000100 <
b10000100 \
b10000100 1
b10000100 W
b10000100 [
#240
0"
#244
1"
#245
b10000100 !
b10000100 5
b10000100 =
b10000100 T
#246
b10001000 4
b10001000 <
b10001000 \
b10001000 1
b10001000 W
b10001000 [
#248
0"
#252
1"
