Group05_Lab5_part3/part3/group05_lab5_part1.v


module ALU(DATA1,DATA2,RESULT,SELECT);

input wire[7:0] DATA1,DATA2; // Declaring an input wire-buses DATA1 and DATA2
input wire[2:0] SELECT; // Declaring an input wire-buse SELECT
output reg[7:0] RESULT; // Declaring an output RESULT as a reg
wire [7:0] FORWARD_wire,ADD_wire,AND_wire,OR_wire; // Declaring wires which connects the multiplexer and Circuits which implement FORWARD,AND,ADD,OR operations


forward f1(DATA2,FORWARD_wire); //Creating an instance of forward module
adder f2(DATA1,DATA2,ADD_wire); //Creating an instance of adder module
AND f3(DATA1,DATA2,AND_wire); //Creating an instance of AND module
OR f4(DATA1,DATA2,OR_wire); //Creating an instance of OR module

//Implementing a multiplexer to select the algrebric operation we need according to SELECT signal
always @(DATA1 or DATA2 or SELECT) begin
    
     case (SELECT)
         3'b000: assign RESULT = FORWARD_wire;
         3'b001: assign RESULT = ADD_wire;
         3'b010: assign RESULT = AND_wire;
         3'b011: assign RESULT = OR_wire;
         default: assign RESULT = 8'bxxxxxxxx; //If SELECT is neither 000,001,010,011, operations to other codes are not assigned yet. Hence Unknown result is generated.
     endcase
end
endmodule

//Module which implemented ADD operation
module adder(DATA1,DATA2,RESULT);
    input wire[7:0] DATA1,DATA2;
    output wire[7:0] RESULT;

    assign #2 RESULT = DATA1+DATA2; //Adding DATA1 and DATA2 inputs with a delay
endmodule

//Module which implemented FORWARD operation
module forward(DATA2,RESULT);
    input wire[7:0] DATA2;
    output wire[7:0] RESULT;

    assign #1 RESULT = DATA2; //Assigning DATA2 to RESULT
endmodule

//Module which implemented AND operation
module AND (DATA1,DATA2,RESULT);
    input wire[7:0] DATA1,DATA2;
    output wire[7:0] RESULT;
    
    assign #1 RESULT = DATA1 & DATA2; //AND DATA1 and DATA2 inputs with a delay
endmodule

//Module which implemented OR operation
module OR (DATA1,DATA2,RESULT);
    input wire[7:0] DATA1,DATA2;
    output wire[7:0] RESULT;
    
    assign #1 RESULT = DATA1 | DATA2; //OR DATA1 and DATA2 inputs with a delay
endmodule

group05_lab06_part02/group05_lab06_part02/group05_lab5_part2.v
`timescale 1ns/100ps

module reg_file(IN, OUT1, OUT2, INADDRESS, OUT1ADDRESS, OUT2ADDRESS, WRITE, CLK, RESET);
    input[7:0] IN; // Declaring an input wire-bus to take WRITEDATA signals
    input[2:0] OUT1ADDRESS,OUT2ADDRESS,INADDRESS; // Declaring an input wire-bus to take WRITEDATA signals
    input CLK,WRITE,RESET; // Declaring clock pulse wire, WRITE_ENABLE wire and RESET wire as input 
    output reg [7:0] OUT1,OUT2;  // Declaring REGOUT1 and REGOUT2 signals as register outputs
    reg[7:0] register[0:7]; // Declaring register0-register7 as an array of words 

    //For rising edges of clock pulse
    always @(posedge CLK) begin
        if(RESET==1)begin //When RESET = 1 clearing registers with a delay

            #1
             register[0]<=0;
             register[1]<=0;
             register[2]<=0;
             register[3]<=0;
             register[4]<=0;
             register[5]<=0;
             register[6]<=0;
             register[7]<=0;
        end
        else if(WRITE==1)begin // When WRITE_ENABLE = 1 writing to a specific register
            
            case(INADDRESS) //Choosing the register to be written by considering the INADDRESS signal
                3'b000:#1 register[0] <= IN;
                3'b001:#1 register[1] <= IN;
                3'b010:#1 register[2] <= IN;
                3'b011:#1 register[3] <= IN;
                3'b100:#1 register[4] <= IN;
                3'b101:#1 register[5] <= IN;
                3'b110:#1 register[6] <= IN;
                3'b111:#1 register[7] <= IN;
                default:;
            endcase
        end
        
    end

    //When changes occur in registers register0-register7 or OUT1ADDRESS, asynchrous reading operating takes place.
    always @(OUT2ADDRESS,OUT1ADDRESS,register[0],register[1],register[2],register[3],register[4],register[5],register[6],register[7]) begin
        case (OUT1ADDRESS) //Choosing the register to be read by considering the OUT1ADDRESS signal
            3'b000:#2 OUT1 = register[0];
            3'b001:#2 OUT1 = register[1];
            3'b010:#2 OUT1 = register[2];
            3'b011:#2 OUT1 = register[3];
            3'b100:#2 OUT1 = register[4];
            3'b101:#2 OUT1 = register[5];
            3'b110:#2 OUT1 = register[6];
            3'b111:#2 OUT1 = register[7]; 
            default:; 
        endcase
    end

    //When changes occur in registers register0-register7 or OUT2ADDRESS, asynchrous reading operating takes place.
    always @(OUT1ADDRESS,OUT2ADDRESS,register[0],register[1],register[2],register[3],register[4],register[5],register[6],register[7]) begin
        case (OUT2ADDRESS) //Choosing the register to be read by considering the OUT2ADDRESS signal
            3'b000:#2 OUT2 = register[0];
            3'b001:#2 OUT2 = register[1];
            3'b010:#2 OUT2 = register[2];
            3'b011:#2 OUT2 = register[3];
            3'b100:#2 OUT2 = register[4];
            3'b101:#2 OUT2 = register[5];
            3'b110:#2 OUT2 = register[6];
            3'b111:#2 OUT2 = register[7]; 
            default:; 
        endcase      
    end

endmodule

Group05_Lab5_part3/part3/group05_lab5_part3.v
//module for the cpu
module cpu(PC , INSTRUCTION , CLK ,RESET) ;
    //declare inputs and outputs 
    input CLK, RESET;
    output [31:0] PC;
    input wire [31:0] INSTRUCTION;

    //declare respective wires

    wire [2:0] READREG1 , READREG2 , WRITEREG ;
    wire [7:0] OPCODE , IMMEDIATE ;
    
    wire [2:0] ALUOP ;
    wire MUX1_select , MUX2_select , WRITEENABLE ;

    wire [7:0] ALURESULT , REGOUT1 , REGOUT2 ;
    
    wire [7:0] REGOUT2_2scomp ;

    wire [7:0] mux1_OUTPUT ;

    wire [7:0] mux2_OUTPUT ;

    //break the instruction to resoective parts and assign for the wires 
    assign READREG2[2:0] = INSTRUCTION[2:0] ;
    assign READREG1[2:0] = INSTRUCTION[10:8] ;
    assign WRITEREG[2:0] = INSTRUCTION[18:16] ;
    assign OPCODE[7:0] = INSTRUCTION[31:24] ;
    assign IMMEDIATE[7:0] = INSTRUCTION[7:0] ;


    //call the respective modules and instantiate respective modules
    pc myPC(CLK ,RESET , PC);
    Control_Unit my_Control_Unit(OPCODE , WRITEENABLE , ALUOP , MUX1_select , MUX2_select);
    reg_file my_reg(ALURESULT, REGOUT1, REGOUT2, WRITEREG, READREG1, READREG2, WRITEENABLE, CLK, RESET);
    TWOS_Comp my_TWOS_Comp(REGOUT2 , REGOUT2_2scomp);
    MUX_7x2x1 my_mux1(REGOUT2 , REGOUT2_2scomp , mux1_OUTPUT , MUX1_select);
    MUX_7x2x1 my_mux2(IMMEDIATE , mux1_OUTPUT , mux2_OUTPUT , MUX2_select);
    ALU my_ALU(REGOUT1,mux2_OUTPUT,ALURESULT,ALUOP);

endmodule

//module for the program counter
module pc (CLK , RESET  , PC);
    input CLK ,RESET;
    output reg[31:0] PC ;
    reg [31:0] PC_val; // made a reg for the pc value


    always @(posedge CLK) begin
        if (RESET==1'b1) begin
            #1 PC = 32'b00000000000000000000000000000000;
        end else begin
            #1  PC = PC_val ;
        end
        
    end

    always @(PC) begin
        
        #1 PC_val = PC + 32'd4 ; //increase the pc value every time when it is changing
        
    end
endmodule


//module for the control unit
module Control_Unit (OPCODE , WRITEENABLE , ALUOP , MUX1_select , MUX2_select);
    input [7:0]OPCODE ;
    output reg [2:0]ALUOP ;
    output reg MUX1_select , MUX2_select , WRITEENABLE;


    always @(OPCODE) begin //selecting respective selecting signals

        case(OPCODE) 
                8'b00000000: begin //loadi
                    #1 
                    WRITEENABLE <= 1'b1; 
                    ALUOP <= 3'b000 ; 
                    //MUX1_select <= 1'b1 ; 
                    MUX2_select <= 1'b1 ; 
                    end

                8'b00000001: begin //mov
                    #1 
                    WRITEENABLE <= 1'b1; 
                    ALUOP <= 3'b000 ; 
                    MUX1_select <= 1'b1 ; 
                    MUX2_select <= 1'b0 ; 
                    end

                8'b00000010: begin //add
                    #1 
                    WRITEENABLE <= 1'b1; 
                    ALUOP <= 3'b001 ; 
                    MUX1_select <= 1'b1 ; 
                    MUX2_select <= 1'b0 ; 
                    end

                8'b00000011: begin //sub
                    #1 
                    WRITEENABLE <= 1'b1; 
                    ALUOP <= 3'b001 ; 
                    MUX1_select <= 1'b0 ; 
                    MUX2_select <= 1'b0 ; 
                    end

                8'b00000100: begin //and
                    #1 
                    WRITEENABLE <= 1'b1; 
                    ALUOP <= 3'b010 ; 
                    MUX1_select <= 1'b1 ; 
                    MUX2_select <= 1'b0 ; 
                    end

                8'b00000101: begin //or
                    #1 
                    WRITEENABLE <= 1'b1; 
                    ALUOP <= 3'b011 ; 
                    MUX1_select <= 1'b1 ; 
                    MUX2_select <= 1'b0 ; 
                    end
               
                default:#1 WRITEENABLE <= 1'b0; 
        endcase
    end

endmodule

//module for the 2s complement
module TWOS_Comp (REGOUT2 , REGOUT2_2scomp);
    input [7:0] REGOUT2 ;
    output [7:0] REGOUT2_2scomp ;

    assign #1  REGOUT2_2scomp = ~REGOUT2 + 8'b00000001  ;

endmodule

//module for the mux
module MUX_7x2x1 (INPUT1 , INPUT2 , OUTPUT , SELECT);
    input [7:0] INPUT1 , INPUT2 ;
    input SELECT ;
    output reg [7:0] OUTPUT ;

    always @(INPUT1 , INPUT2,SELECT) begin
        if(SELECT==1'b1)begin
            assign OUTPUT = INPUT1;
        end else if (SELECT==1'b0) begin
            assign OUTPUT = INPUT2;
        end
    end

endmodule





// Computer Architecture (CO224) - Lab 05
// Design: Testbench of Integrated CPU of Simple Processor
// Author: Isuru Nawinne


module cpu_tb;

    reg CLK, RESET;
    wire [31:0] PC;
    reg [31:0] INSTRUCTION;
    reg [7:0] instr_mem [1024:0] ;
    
    /* 
    ------------------------
     SIMPLE INSTRUCTION MEM
    ------------------------
    */
    
    // TODO: Initialize an array of registers (8x1024) named 'instr_mem' to be used as instruction memory
    
    // TODO: Create combinational logic to support CPU instruction fetching, given the Program Counter(PC) value 
    //       (make sure you include the delay for instruction fetching here)
    
    always @(PC) begin
        #2
        INSTRUCTION[7:0]<=instr_mem[PC] ;
        INSTRUCTION[15:8]<=instr_mem[PC+31'd1] ;
        INSTRUCTION[23:16]<=instr_mem[PC+31'd2] ;
        INSTRUCTION[31:24]<=instr_mem[PC+31'd3] ;
    end

    initial
    begin
        // Initialize instruction memory with the set of instructions you need execute on CPU
        
        // METHOD 1: manually loading instructions to instr_mem
        //{instr_mem[10'd3], instr_mem[10'd2], instr_mem[10'd1], instr_mem[10'd0]} = 32'b00000000000001000000000000000101;
        //{instr_mem[10'd7], instr_mem[10'd6], instr_mem[10'd5], instr_mem[10'd4]} = 32'b00000000000000100000000000001001;
        //{instr_mem[10'd11], instr_mem[10'd10], instr_mem[10'd9], instr_mem[10'd8]} = 32'b00000010000001100000010000000010;
        
        // METHOD 2: loading instr_mem content from instr_mem.mem file
        $readmemb("instr_mem.mem", instr_mem,0,256);
    end
    
    /* 
    -----
     CPU
    -----
    */
    cpu mycpu(PC, INSTRUCTION, CLK, RESET);
    

    initial
    begin
    
        // generate files needed to plot the waveform using GTKWave
        $dumpfile("cpu_wavedata.vcd");
		$dumpvars(0, cpu_tb);
        
        CLK = 1'b0;
        //RESET = 1'b0;

        RESET = 1'b1;
        #10 RESET = 1'b0;
        
        // TODO: Reset the CPU (by giving a pulse to RESET signal) to start the program execution
        
        // finish simulation after some time
        #500
        $finish;
        
    end
    
    // clock signal generation
    always
        #4 CLK = ~CLK;
        

endmodule

Group05_Lab5_part3/part3/cpu_wavedata.vcd
$date
	Tue Jan 25 22:26:41 2022
$end
$version
	Icarus Verilog
$end
$timescale
	1s
$end
$scope module cpu_tb $end
$var wire 32 ! PC [31:0] $end
$var reg 1 " CLK $end
$var reg 32 # INSTRUCTION [31:0] $end
$var reg 1 $ RESET $end
$scope module mycpu $end
$var wire 1 " CLK $end
$var wire 32 % INSTRUCTION [31:0] $end
$var wire 1 $ RESET $end
$var wire 8 & mux2_OUTPUT [7:0] $end
$var wire 8 ' mux1_OUTPUT [7:0] $end
$var wire 3 ( WRITEREG [2:0] $end
$var wire 1 ) WRITEENABLE $end
$var wire 8 * REGOUT2_2scomp [7:0] $end
$var wire 8 + REGOUT2 [7:0] $end
$var wire 8 , REGOUT1 [7:0] $end
$var wire 3 - READREG2 [2:0] $end
$var wire 3 . READREG1 [2:0] $end
$var wire 32 / PC [31:0] $end
$var wire 8 0 OPCODE [7:0] $end
$var wire 1 1 MUX2_select $end
$var wire 1 2 MUX1_select $end
$var wire 8 3 IMMEDIATE [7:0] $end
$var wire 8 4 ALURESULT [7:0] $end
$var wire 3 5 ALUOP [2:0] $end
$scope module myPC $end
$var wire 1 " CLK $end
$var wire 1 $ RESET $end
$var reg 32 6 PC [31:0] $end
$var reg 32 7 PC_val [31:0] $end
$upscope $end
$scope module my_ALU $end
$var wire 3 8 SELECT [2:0] $end
$var wire 8 9 OR_wire [7:0] $end
$var wire 8 : FORWARD_wire [7:0] $end
$var wire 8 ; DATA2 [7:0] $end
$var wire 8 < DATA1 [7:0] $end
$var wire 8 = AND_wire [7:0] $end
$var wire 8 > ADD_wire [7:0] $end
$var reg 8 ? RESULT [7:0] $end
$scope module f1 $end
$var wire 8 @ RESULT [7:0] $end
$var wire 8 A DATA2 [7:0] $end
$upscope $end
$scope module f2 $end
$var wire 8 B RESULT [7:0] $end
$var wire 8 C DATA2 [7:0] $end
$var wire 8 D DATA1 [7:0] $end
$upscope $end
$scope module f3 $end
$var wire 8 E RESULT [7:0] $end
$var wire 8 F DATA2 [7:0] $end
$var wire 8 G DATA1 [7:0] $end
$upscope $end
$scope module f4 $end
$var wire 8 H RESULT [7:0] $end
$var wire 8 I DATA2 [7:0] $end
$var wire 8 J DATA1 [7:0] $end
$upscope $end
$upscope $end
$scope module my_Control_Unit $end
$var wire 8 K OPCODE [7:0] $end
$var reg 3 L ALUOP [2:0] $end
$var reg 1 2 MUX1_select $end
$var reg 1 1 MUX2_select $end
$var reg 1 ) WRITEENABLE $end
$upscope $end
$scope module my_TWOS_Comp $end
$var wire 8 M REGOUT2_2scomp [7:0] $end
$var wire 8 N REGOUT2 [7:0] $end
$upscope $end
$scope module my_mux1 $end
$var wire 8 O INPUT2 [7:0] $end
$var wire 1 2 SELECT $end
$var wire 8 P INPUT1 [7:0] $end
$var reg 8 Q OUTPUT [7:0] $end
$upscope $end
$scope module my_mux2 $end
$var wire 8 R INPUT1 [7:0] $end
$var wire 8 S INPUT2 [7:0] $end
$var wire 1 1 SELECT $end
$var reg 8 T OUTPUT [7:0] $end
$upscope $end
$scope module my_reg $end
$var wire 1 " CLK $end
$var wire 8 U IN [7:0] $end
$var wire 3 V INADDRESS [2:0] $end
$var wire 3 W OUT1ADDRESS [2:0] $end
$var wire 3 X OUT2ADDRESS [2:0] $end
$var wire 1 $ RESET $end
$var wire 1 ) WRITE $end
$var reg 8 Y OUT1 [7:0] $end
$var reg 8 Z OUT2 [7:0] $end
$upscope $end
$upscope $end
$upscope $end
$enddefinitions $end
#0
$dumpvars
bx Z
bx Y
bx X
bx W
bx V
bx U
bx T
bx S
bx R
bx Q
bx P
bx O
bx N
bx M
bx L
bx K
bx J
bx I
bx H
bx G
bx F
bx E
bx D
bx C
bx B
bx A
bx @
bx ?
bx >
bx =
bx <
bx ;
bx :
bx 9
bx 8
bx 7
bx 6
bx 5
bx 4
bx 3
x2
x1
bx 0
bx /
bx .
bx -
bx ,
bx +
bx *
x)
bx (
bx '
bx &
bx %
1$
bx #
0"
bx !
$end
#4
1"
#5
b0 !
b0 /
b0 6
#6
b100 7
#7
b0 0
b0 K
b0 (
b0 V
b0 .
b0 W
b101 -
b101 X
b101 3
b101 R
b101 #
b101 %
#8
b101 &
b101 ;
b101 A
b101 C
b101 F
b101 I
b101 T
11
b0 5
b0 8
b0 L
1)
0"
#9
bx1x1 9
bx1x1 H
b0x0x =
b0x0x E
b101 4
b101 ?
b101 U
b101 :
b101 @
b0 ,
b0 <
b0 D
b0 G
b0 J
b0 Y
b0 +
b0 N
b0 P
b0 Z
#10
b101 9
b101 H
b0 =
b0 E
b0 *
b0 M
b0 O
0$
#11
b101 >
b101 B
#12
1"
#13
b100 !
b100 /
b100 6
#14
b1000 7
#15
b1 0
b1 K
b1 (
b1 V
b0 -
b0 X
b0 &
b0 ;
b0 A
b0 C
b0 F
b0 I
b0 T
b0 3
b0 R
b1000000010000000000000000 #
b1000000010000000000000000 %
b101 ,
b101 <
b101 D
b101 G
b101 J
b101 Y
#16
b0 '
b0 Q
b0 S
01
12
b0 4
b0 ?
b0 U
b0 :
b0 @
0"
#17
b101 &
b101 ;
b101 A
b101 C
b101 F
b101 I
b101 T
b101 '
b101 Q
b101 S
b101 +
b101 N
b101 P
b101 Z
#18
b11111011 *
b11111011 M
b11111011 O
b101 =
b101 E
b101 4
b101 ?
b101 U
b101 :
b101 @
#19
b1010 >
b1010 B
#20
1"
#21
b1000 !
b1000 /
b1000 6
#22
b1100 7
#23
b0 0
b0 K
b10 (
b10 V
b1 -
b1 X
b1001 3
b1001 R
b100000000000001001 #
b100000000000001001 %
#24
b1001 &
b1001 ;
b1001 A
b1001 C
b1001 F
b1001 I
b1001 T
11
0"
#25
b1101 9
b1101 H
b1 =
b1 E
b1001 4
b1001 ?
b1001 U
b1001 :
b1001 @
#26
b1110 >
b1110 B
#28
1"
#29
b1100 !
b1100 /
b1100 6
#30
b10000 7
#31
b10 0
b10 K
b11 (
b11 V
b10 .
b10 W
b0 -
b0 X
b0 &
b0 ;
b0 A
b0 C
b0 F
b0 I
b0 T
b0 3
b0 R
b10000000110000001000000000 #
b10000000110000001000000000 %
#32
b101 &
b101 ;
b101 A
b101 C
b101 F
b101 I
b101 T
01
b1 5
b1 8
b1 L
b101 9
b101 H
b0 =
b0 E
b1110 4
b1110 ?
b1110 U
b0 :
b0 @
0"
#33
b101 =
b101 E
b101 :
b101 @
b1001 ,
b1001 <
b1001 D
b1001 G
b1001 J
b1001 Y
#34
b1101 9
b1101 H
b1 =
b1 E
#36
1"
#37
b10000 !
b10000 /
b10000 6
#38
b10100 7
#39
b11 0
b11 K
b100 (
b100 V
b11 .
b11 W
b10 -
b10 X
b10 3
b10 R
b11000001000000001100000010 #
b11000001000000001100000010 %
#40
b11111011 &
b11111011 ;
b11111011 A
b11111011 C
b11111011 F
b11111011 I
b11111011 T
b11111011 '
b11111011 Q
b11111011 S
02
0"
#41
b11111011 9
b11111011 H
b1001 =
b1001 E
b11111011 :
b11111011 @
b1110 ,
b1110 <
b1110 D
b1110 G
b1110 J
b1110 Y
b1001 +
b1001 N
b1001 P
b1001 Z
#42
b11111111 9
b11111111 H
b1010 =
b1010 E
b11110111 &
b11110111 ;
b11110111 A
b11110111 C
b11110111 F
b11110111 I
b11110111 T
b11110111 '
b11110111 Q
b11110111 S
b11110111 *
b11110111 M
b11110111 O
#43
b110 =
b110 E
b11110111 :
b11110111 @
#44
b101 4
b101 ?
b101 U
b101 >
b101 B
1"
#45
b10100 !
b10100 /
b10100 6
#46
b11000 7
#47
b100 0
b100 K
b101 (
b101 V
b10 .
b10 W
b1 -
b1 X
b1 3
b1 R
b100000001010000001000000001 #
b100000001010000001000000001 %
#48
b1001 &
b1001 ;
b1001 A
b1001 C
b1001 F
b1001 I
b1001 T
b1001 '
b1001 Q
b1001 S
b110 4
b110 ?
b110 U
12
b10 5
b10 8
b10 L
0"
#49
b1111 9
b1111 H
b1000 4
b1000 ?
b1000 U
b1000 =
b1000 E
b1001 :
b1001 @
b1001 ,
b1001 <
b1001 D
b1001 G
b1001 J
b1001 Y
b101 &
b101 ;
b101 A
b101 C
b101 F
b101 I
b101 T
b101 '
b101 Q
b101 S
b101 +
b101 N
b101 P
b101 Z
#50
b11111011 *
b11111011 M
b11111011 O
b1101 9
b1101 H
b1 4
b1 ?
b1 U
b1 =
b1 E
b101 :
b101 @
#51
b1110 >
b1110 B
#52
1"
#53
b11000 !
b11000 /
b11000 6
#54
b11100 7
#55
b101 0
b101 K
b110 (
b110 V
b101 .
b101 W
b0 -
b0 X
b0 3
b0 R
b101000001100000010100000000 #
b101000001100000010100000000 %
#56
b1101 4
b1101 ?
b1101 U
b11 5
b11 8
b11 L
0"
#57
b1 ,
b1 <
b1 D
b1 G
b1 J
b1 Y
#58
b101 4
b101 ?
b101 U
b101 9
b101 H
#59
b110 >
b110 B
#60
1"
#61
b11100 !
b11100 /
b11100 6
#62
b100000 7
#63
bx 0
bx K
bx (
bx V
bx .
bx W
bx -
bx X
bx 3
bx R
bx #
bx %
#64
0)
0"
#68
1"
#69
b100000 !
b100000 /
b100000 6
#70
b100100 7
#72
0"
#76
1"
#77
b100100 !
b100100 /
b100100 6
#78
b101000 7
#80
0"
#84
1"
#85
b101000 !
b101000 /
b101000 6
#86
b101100 7
#88
0"
#92
1"
#93
b101100 !
b101100 /
b101100 6
#94
b110000 7
#96
0"
#100
1"
#101
b110000 !
b110000 /
b110000 6
#102
b110100 7
#104
0"
#108
1"
#109
b110100 !
b110100 /
b110100 6
#110
b111000 7
#112
0"
#116
1"
#117
b111000 !
b111000 /
b111000 6
#118
b111100 7
#120
0"
#124
1"
#125
b111100 !
b111100 /
b111100 6
#126
b1000000 7
#128
0"
#132
1"
#133
b1000000 !
b1000000 /
b1000000 6
#134
b1000100 7
#136
0"
#140
1"
#141
b1000100 !
b1000100 /
b1000100 6
#142
b1001000 7
#144
0"
#148
1"
#149
b1001000 !
b1001000 /
b1001000 6
#150
b1001100 7
#152
0"
#156
1"
#157
b1001100 !
b1001100 /
b1001100 6
#158
b1010000 7
#160
0"
#164
1"
#165
b1010000 !
b1010000 /
b1010000 6
#166
b1010100 7
#168
0"
#172
1"
#173
b1010100 !
b1010100 /
b1010100 6
#174
b1011000 7
#176
0"
#180
1"
#181
b1011000 !
b1011000 /
b1011000 6
#182
b1011100 7
#184
0"
#188
1"
#189
b1011100 !
b1011100 /
b1011100 6
#190
b1100000 7
#192
0"
#196
1"
#197
b1100000 !
b1100000 /
b1100000 6
#198
b1100100 7
#200
0"
#204
1"
#205
b1100100 !
b1100100 /
b1100100 6
#206
b1101000 7
#208
0"
#212
1"
#213
b1101000 !
b1101000 /
b1101000 6
#214
b1101100 7
#216
0"
#220
1"
#221
b1101100 !
b1101100 /
b1101100 6
#222
b1110000 7
#224
0"
#228
1"
#229
b1110000 !
b1110000 /
b1110000 6
#230
b1110100 7
#232
0"
#236
1"
#237
b1110100 !
b1110100 /
b1110100 6
#238
b1111000 7
#240
0"
#244
1"
#245
b1111000 !
b1111000 /
b1111000 6
#246
b1111100 7
#248
0"
#252
1"
#253
b1111100 !
b1111100 /
b1111100 6
#254
b10000000 7
#256
0"
#260
1"
#261
b10000000 !
b10000000 /
b10000000 6
#262
b10000100 7
#264
0"
#268
1"
#269
b10000100 !
b10000100 /
b10000100 6
#270
b10001000 7
#272
0"
#276
1"
#277
b10001000 !
b10001000 /
b10001000 6
#278
b10001100 7
#280
0"
#284
1"
#285
b10001100 !
b10001100 /
b10001100 6
#286
b10010000 7
#288
0"
#292
1"
#293
b10010000 !
b10010000 /
b10010000 6
#294
b10010100 7
#296
0"
#300
1"
#301
b10010100 !
b10010100 /
b10010100 6
#302
b10011000 7
#304
0"
#308
1"
#309
b10011000 !
b10011000 /
b10011000 6
#310
b10011100 7
#312
0"
#316
1"
#317
b10011100 !
b10011100 /
b10011100 6
#318
b10100000 7
#320
0"
#324
1"
#325
b10100000 !
b10100000 /
b10100000 6
#326
b10100100 7
#328
0"
#332
1"
#333
b10100100 !
b10100100 /
b10100100 6
#334
b10101000 7
#336
0"
#340
1"
#341
b10101000 !
b10101000 /
b10101000 6
#342
b10101100 7
#344
0"
#348
1"
#349
b10101100 !
b10101100 /
b10101100 6
#350
b10110000 7
#352
0"
#356
1"
#357
b10110000 !
b10110000 /
b10110000 6
#358
b10110100 7
#360
0"
#364
1"
#365
b10110100 !
b10110100 /
b10110100 6
#366
b10111000 7
#368
0"
#372
1"
#373
b10111000 !
b10111000 /
b10111000 6
#374
b10111100 7
#376
0"
#380
1"
#381
b10111100 !
b10111100 /
b10111100 6
#382
b11000000 7
#384
0"
#388
1"
#389
b11000000 !
b11000000 /
b11000000 6
#390
b11000100 7
#392
0"
#396
1"
#397
b11000100 !
b11000100 /
b11000100 6
#398
b11001000 7
#400
0"
#404
1"
#405
b11001000 !
b11001000 /
b11001000 6
#406
b11001100 7
#408
0"
#412
1"
#413
b11001100 !
b11001100 /
b11001100 6
#414
b11010000 7
#416
0"
#420
1"
#421
b11010000 !
b11010000 /
b11010000 6
#422
b11010100 7
#424
0"
#428
1"
#429
b11010100 !
b11010100 /
b11010100 6
#430
b11011000 7
#432
0"
#436
1"
#437
b11011000 !
b11011000 /
b11011000 6
#438
b11011100 7
#440
0"
#444
1"
#445
b11011100 !
b11011100 /
b11011100 6
#446
b11100000 7
#448
0"
#452
1"
#453
b11100000 !
b11100000 /
b11100000 6
#454
b11100100 7
#456
0"
#460
1"
#461
b11100100 !
b11100100 /
b11100100 6
#462
b11101000 7
#464
0"
#468
1"
#469
b11101000 !
b11101000 /
b11101000 6
#470
b11101100 7
#472
0"
#476
1"
#477
b11101100 !
b11101100 /
b11101100 6
#478
b11110000 7
#480
0"
#484
1"
#485
b11110000 !
b11110000 /
b11110000 6
#486
b11110100 7
#488
0"
#492
1"
#493
b11110100 !
b11110100 /
b11110100 6
#494
b11111000 7
#496
0"
#500
1"
#501
b11111000 !
b11111000 /
b11111000 6
#502
b11111100 7
#504
0"
#508
1"
#509
b11111100 !
b11111100 /
b11111100 6
#510
b100000000 7
